quiz_project/__init__.py
quiz_project/main.py
quiz_project/play/__init__.py
quiz_project/play/check_input.py
quiz_project/play/play_quiz.py
quiz_project/play/start.py
quiz_project-0.0.3.1.dist-info/METADATA
quiz_project-0.0.3.1.dist-info/WHEEL
quiz_project-0.0.3.1.dist-info/top_level.txt
quiz_project-0.0.3.1.dist-info/RECORD
