Metadata-Version: 2.1
Name: quiz_project
Version: 0.0.3.1
Summary: Quiz creator and displayer
Author: Mariana Aguerrevere
Author-email: aamariana1907@gmail.com
Keywords: python,quiz,creator,display,game
